CHANGES.rst
CONTRIBUTORS.rst
LICENSE.txt
MANIFEST.in
README.rst
bootstrap.py
buildout.cfg
setup.py
buildout/__init__.py
buildout.dumppickedversions2.egg-info/PKG-INFO
buildout.dumppickedversions2.egg-info/SOURCES.txt
buildout.dumppickedversions2.egg-info/dependency_links.txt
buildout.dumppickedversions2.egg-info/entry_points.txt
buildout.dumppickedversions2.egg-info/namespace_packages.txt
buildout.dumppickedversions2.egg-info/not-zip-safe
buildout.dumppickedversions2.egg-info/requires.txt
buildout.dumppickedversions2.egg-info/top_level.txt
buildout/dumppickedversions2/__init__.py
buildout/dumppickedversions2/dumppickedversions2.rst
buildout/dumppickedversions2/tests.py