Metadata-Version: 1.1
Name: buildout.dumppickedversions2
Version: 1.1
Summary: Dump buildout 2 picked versions.
Home-page: https://github.com/eightmedia/buildout.dumppickedversions2
Author: Jaap Roes
Author-email: jaap@eight.nl
License: MIT
Keywords: buildout extension dump picked versions
Platform: UNKNOWN
Classifier: Framework :: Buildout
Classifier: Intended Audience :: Developers
